LICENSE
README.md
setup.py
tablexplore/__init__.py
tablexplore/app.py
tablexplore/core.py
tablexplore/dialogs.py
tablexplore/interpreter.py
tablexplore/logo.png
tablexplore/logo.svg
tablexplore/plotting.py
tablexplore/plugin.py
tablexplore/qt.py
tablexplore/terminal.py
tablexplore/util.py
tablexplore/widgets.py
tablexplore.egg-info/PKG-INFO
tablexplore.egg-info/SOURCES.txt
tablexplore.egg-info/dependency_links.txt
tablexplore.egg-info/entry_points.txt
tablexplore.egg-info/requires.txt
tablexplore.egg-info/top_level.txt
tablexplore/../description.txt
tablexplore/datasets/co2-ppm-mauna-loa.csv
tablexplore/datasets/iris.csv
tablexplore/datasets/pima.csv
tablexplore/datasets/titanic.csv
tablexplore/icons/add-column.png
tablexplore/icons/add-row.png
tablexplore/icons/add.png
tablexplore/icons/aggregate.png
tablexplore/icons/application-exit.png
tablexplore/icons/arrow-down.png
tablexplore/icons/arrow-up.png
tablexplore/icons/clean.png
tablexplore/icons/clear.png
tablexplore/icons/close.png
tablexplore/icons/copy.png
tablexplore/icons/decrease-width.png
tablexplore/icons/delete.png
tablexplore/icons/document-new.png
tablexplore/icons/document-open.png
tablexplore/icons/document-save.png
tablexplore/icons/enlarge.png
tablexplore/icons/excel.png
tablexplore/icons/export.png
tablexplore/icons/filter.png
tablexplore/icons/find.png
tablexplore/icons/findall.png
tablexplore/icons/findreplace.png
tablexplore/icons/increase-width.png
tablexplore/icons/interpreter.png
tablexplore/icons/lock.png
tablexplore/icons/logo.png
tablexplore/icons/lowercase.png
tablexplore/icons/melt.png
tablexplore/icons/merge.png
tablexplore/icons/open.png
tablexplore/icons/paste.png
tablexplore/icons/pivot.png
tablexplore/icons/plot-map.png
tablexplore/icons/plot.png
tablexplore/icons/plotseries.png
tablexplore/icons/preferences-system.png
tablexplore/icons/project-new.png
tablexplore/icons/reduce.png
tablexplore/icons/remove.png
tablexplore/icons/save-all.png
tablexplore/icons/save.png
tablexplore/icons/scratchpad-plot.png
tablexplore/icons/scratchpad-table.png
tablexplore/icons/scratchpad.png
tablexplore/icons/subtable.png
tablexplore/icons/table-duplicates.png
tablexplore/icons/table-filter.png
