Metadata-Version: 2.1
Name: tablexplore
Version: 0.5.1
Summary: Table analysis and plotting application written in PySide2/PyQt5
Home-page: https://github.com/dmnfarrell/tablexplore
Author: Damien Farrell
Author-email: farrell.damien@gmail.com
License: GPL v3
Keywords: spreadsheet,table,pandas,data analysis,qt
Platform: UNKNOWN
Classifier: Operating System :: OS Independent
Classifier: Programming Language :: Python :: 3
Classifier: Operating System :: MacOS :: MacOS X
Classifier: Operating System :: Microsoft :: Windows
Classifier: Operating System :: POSIX
Classifier: Topic :: Software Development :: User Interfaces
Classifier: License :: OSI Approved :: GNU General Public License v3 (GPLv3)
Classifier: Development Status :: 4 - Beta
Classifier: Intended Audience :: Science/Research
License-File: LICENSE
